bpctl_test-1.3.5.data/scripts/bpctl
lib/__init__.py
lib/bpctl/__init__.py
lib/bpctl/authenticate.py
lib/bpctl/base.py
lib/bpctl/bp_manifest.py
lib/bpctl/bpctl.py
lib/bpctl/config.py
lib/bpctl/load_data.py
lib/bpctl/read_bp_yaml.py
lib/bpctl/utils.py
bpctl_test-1.3.5.dist-info/METADATA
bpctl_test-1.3.5.dist-info/WHEEL
bpctl_test-1.3.5.dist-info/top_level.txt
bpctl_test-1.3.5.dist-info/RECORD
